{
    "events": [
        {
            "id": "web_1",
            "title": "VIETBUILD HCM 2025 – Triển lãm quốc tế chuyên ngành xây dựng tại TP. HCM",
            "description": "Hồ Chí MinhVIETBUILD HCM 2025 – Triển lãm quốc tế chuyên ngành xây dựng tại TP. HCMVào cổng tự do626 tham gia",
            "date": ""
        },
        {
            "id": "web_2",
            "title": "VILOG 2025 – Triển lãm Quốc tế Logistics Việt Nam",
            "description": "Hồ Chí MinhVILOG 2025 – Triển lãm Quốc tế Logistics Việt NamĐăng ký tham quan234 tham gia",
            "date": ""
        },
        {
            "id": "web_3",
            "title": "ZHEJIANG EXPORT (VIETNAM) FAIR 2025 – Hội chợ Giao dịch Hàng Xuất khẩu Chiết Giang",
            "description": "Hồ Chí MinhZHEJIANG EXPORT (VIETNAM) FAIR 2025 – Hội chợ Giao dịch Hàng Xuất khẩu Chiết GiangĐăng ký tham quan108 tham gia",
            "date": ""
        },
        {
            "id": "web_4",
            "title": "VIETNAM SPORT SHOW 2025 – Triển lãm quốc tế Thiết bị & Sản phẩm thể thao Việt Nam",
            "description": "Hồ Chí MinhVIETNAM SPORT SHOW 2025 – Triển lãm quốc tế Thiết bị & Sản phẩm thể thao Việt NamĐăng ký tham quan183 tham gia",
            "date": ""
        },
        {
            "id": "web_5",
            "title": "VIETNAM CYCLE EXPO 2025 – Triển lãm quốc tế Xe hai bánh Việt Nam",
            "description": "Hồ Chí MinhVIETNAM CYCLE EXPO 2025 – Triển lãm quốc tế Xe hai bánh Việt NamĐăng ký tham quan383 tham gia",
            "date": ""
        },
        {
            "id": "web_6",
            "title": "VIETBUILD HANOI 2025 – Triển lãm quốc tế chuyên ngành xây dựng tại Hà Nội",
            "description": "Hà NộiVIETBUILD HANOI 2025 – Triển lãm quốc tế chuyên ngành xây dựng tại Hà NộiVào cổng tự do334 tham gia",
            "date": ""
        },
        {
            "id": "web_7",
            "title": "IEAE HANOI 2025 – Triển lãm Quốc Tế Điện Tử & Thiết Bị Thông Minh Việt Nam tại Hà Nội",
            "description": "Hà NộiIEAE HANOI 2025 – Triển lãm Quốc Tế Điện Tử & Thiết Bị Thông Minh Việt Nam tại Hà NộiĐăng ký tham quan150 tham gia",
            "date": ""
        },
        {
            "id": "web_8",
            "title": "VIETNAM EXPO HCM 2025 – Hội chợ Thương mại Quốc tế Việt Nam tại TP. Hồ Chí Minh",
            "description": "Hồ Chí MinhVIETNAM EXPO HCM 2025 – Hội chợ Thương mại Quốc tế Việt Nam tại TP. Hồ Chí MinhĐăng ký tham quan324 tham gia",
            "date": ""
        }
    ]
}